{
    "name": "zhanbujia",
    "power": "奇迹、诡秘、愚弄",
    "taluopai": "愚者",
    "top": "克莱恩",
    "orderby": 1,
    "order": [
        {
            "num": 9,
            "name": "占卜家",
            "func": "",
            "main": [
                ""
            ],
            "assist": [
                ""
            ],
            "ceremony": ""
        },
        {
            "num": 8,
            "name": "小丑",
            "func": "",
            "main": [
                ""
            ],
            "assist": [
                ""
            ],
            "ceremony": ""
        },
        {
            "num": 7,
            "name": "魔术师",
            "func": "",
            "main": [
                ""
            ],
            "assist": [
                ""
            ],
            "ceremony": ""
        },
        {
            "num": 6,
            "name": "无面人",
            "func": "",
            "main": [
                ""
            ],
            "assist": [
                ""
            ],
            "ceremony": ""
        },
        {
            "num": 5,
            "name": "秘偶大师",
            "func": "",
            "main": [
                ""
            ],
            "assist": [
                ""
            ],
            "ceremony": ""
        },
        {
            "num": 4,
            "name": "诡法师",
            "func": "",
            "main": [
                ""
            ],
            "assist": [
                ""
            ],
            "ceremony": ""
        },
        {
            "num": 3,
            "name": "古代学者",
            "func": "",
            "main": [
                ""
            ],
            "assist": [
                ""
            ],
            "ceremony": ""
        },
        {
            "num": 2,
            "name": "奇迹师",
            "func": "",
            "main": [
                ""
            ],
            "assist": [
                ""
            ],
            "ceremony": ""
        },
        {
            "num": 1,
            "name": "诡秘侍者",
            "func": "",
            "main": [
                ""
            ],
            "assist": [
                ""
            ],
            "ceremony": ""
        },
        {
            "num": 0,
            "name": "愚者",
            "func": "",
            "main": [
                ""
            ],
            "assist": [
                ""
            ],
            "ceremony": ""
        }
    ]
}